{
	"name": "pipelineProduct",
	"properties": {
		"activities": [
			{
				"name": "CopyProduct",
				"type": "Copy",
				"dependsOn": [],
				"policy": {
					"timeout": "7.00:00:00",
					"retry": 0,
					"retryIntervalInSeconds": 30,
					"secureOutput": false,
					"secureInput": false
				},
				"userProperties": [],
				"typeProperties": {
					"source": {
						"type": "DelimitedTextSource",
						"storeSettings": {
							"type": "AzureFileStorageReadSettings",
							"recursive": true
						},
						"formatSettings": {
							"type": "DelimitedTextReadSettings"
						}
					},
					"sink": {
						"type": "AzureTableSink",
						"azureTableInsertType": "merge",
						"writeBatchSize": 10000
					},
					"enableStaging": false,
					"translator": {
						"type": "TabularTranslator",
						"mappings": [
							{
								"source": {
									"name": ""
								},
								"sink": {
									"name": "PartitionKey",
									"type": "String"
								}
							},
							{
								"source": {
									"name": "ProductID",
									"type": "String"
								},
								"sink": {
									"name": "RowKey",
									"type": "String"
								}
							},
							{
								"sink": {
									"name": "Timestamp",
									"type": "DateTimeOffset"
								}
							},
							{
								"source": {
									"name": "CategoryID",
									"type": "String"
								},
								"sink": {
									"name": "CategoryID",
									"type": "Int32"
								}
							},
							{
								"source": {
									"name": "Discontinued",
									"type": "String"
								},
								"sink": {
									"name": "Discontinued",
									"type": "Boolean"
								}
							},
							{
								"source": {
									"name": "ProductName",
									"type": "String"
								},
								"sink": {
									"name": "ProductName",
									"type": "String"
								}
							},
							{
								"source": {
									"name": "QuantityPerUnit",
									"type": "String"
								},
								"sink": {
									"name": "QuantityPerUnit",
									"type": "String"
								}
							},
							{
								"source": {
									"name": "ReorderLevel",
									"type": "String"
								},
								"sink": {
									"name": "ReorderLevel",
									"type": "Double"
								}
							},
							{
								"source": {
									"name": "SupplierID",
									"type": "String"
								},
								"sink": {
									"name": "SupplierID",
									"type": "Int32"
								}
							},
							{
								"source": {
									"name": "UnitPrice",
									"type": "String"
								},
								"sink": {
									"name": "UnitPrice",
									"type": "Double"
								}
							},
							{
								"source": {
									"name": "UnitsInStock",
									"type": "String"
								},
								"sink": {
									"name": "UnitsInStock",
									"type": "Double"
								}
							},
							{
								"source": {
									"name": "UnitsOnOrder",
									"type": "String"
								},
								"sink": {
									"name": "UnitsOnOrder",
									"type": "Double"
								}
							}
						]
					}
				},
				"inputs": [
					{
						"referenceName": "NTCL_Product",
						"type": "DatasetReference"
					}
				],
				"outputs": [
					{
						"referenceName": "AzureTable_Product",
						"type": "DatasetReference"
					}
				]
			}
		],
		"parameters": {
			"OrderGroupID": {
				"type": "string",
				"defaultValue": "1"
			}
		},
		"annotations": []
	}
}